meme_get/__init__.py
meme_get/batch.py
meme_get/config.ini
meme_get/meme-util.py
meme_get/memesites.py
meme_get/ocrtest.py
meme_get/praw_test.py
meme_get/test.py
meme_get/ocr/__init__.py
meme_get/ocr/charsimilarity.py
meme_get/ocr/memeocr.py
meme_get/ocr/ocrcomp.py
meme_get/ocr/parse.py
meme_get/ocr/similarity.json
meme_get/ocr/util.py
meme_get/ocr/wordpair.py
meme_get/ocr/dict/linuxwords.txt
meme_get/ocr/dict/urban_dict.txt
meme_get/ocr/dict/words.txt
meme_get/ocr/fonts/Impact.ttf
meme_get-1.0.1b1.dist-info/DESCRIPTION.rst
meme_get-1.0.1b1.dist-info/METADATA
meme_get-1.0.1b1.dist-info/RECORD
meme_get-1.0.1b1.dist-info/WHEEL
meme_get-1.0.1b1.dist-info/metadata.json
meme_get-1.0.1b1.dist-info/top_level.txt
